yediemin/__init__.py
yediemin/serializers.py
yediemin/settings.py
yediemin/storages.py
yediemin/views.py
yediemin-0.2.0.dist-info/LICENSE
yediemin-0.2.0.dist-info/WHEEL
yediemin-0.2.0.dist-info/METADATA
yediemin-0.2.0.dist-info/RECORD
