Metadata-Version: 2.1
Name: yediemin
Version: 0.2.0
Summary: Bulletproof attachment serving for Django Rest Framework.
Home-page: https://github.com/hipo/yediemin
License: MIT
Keywords: python,django,django rest framework,file,attachment
Author: Efe Öge
Author-email: efe@hipolabs.com
Requires-Python: >=3.4,<4
Classifier: Framework :: Django
Classifier: License :: OSI Approved :: Apache Software License
Classifier: License :: OSI Approved :: MIT License
Classifier: Operating System :: OS Independent
Classifier: Programming Language :: Python
Classifier: Programming Language :: Python :: 3
Classifier: Programming Language :: Python :: 3.4
Classifier: Programming Language :: Python :: 3.5
Classifier: Programming Language :: Python :: 3.6
Classifier: Programming Language :: Python :: 3.7
Classifier: Programming Language :: Python :: 3.8
Classifier: Programming Language :: Python :: 3.9
Classifier: Topic :: Internet :: WWW/HTTP
Classifier: Topic :: Internet :: WWW/HTTP :: Dynamic Content
Classifier: Topic :: Software Development :: Libraries :: Python Modules
Requires-Dist: Django (>=1.8)
Requires-Dist: django-storages (>=1.11)
Requires-Dist: djangorestframework (>=3.0)
Project-URL: Repository, https://github.com/hipo/yediemin
